mnmstpy/MNMST_CPU.py
mnmstpy/MNMST_GPU.py
mnmstpy/__init__.py
mnmstpy/network.py
mnmstpy/utils.py
mnmstpy-1.1.0.dist-info/LICENSE
mnmstpy-1.1.0.dist-info/METADATA
mnmstpy-1.1.0.dist-info/WHEEL
mnmstpy-1.1.0.dist-info/top_level.txt
mnmstpy-1.1.0.dist-info/RECORD
