Metadata-Version: 2.1
Name: mnmstpy
Version: 1.1.0
Summary: The initial package of MNMST
Author-email: Yu Wang <qq352542417@gmail.com>
Project-URL: Homepage, https://github.com/xkmaxidian/MNMST
Project-URL: Issues, https://github.com/xkmaxidian/MNMST/issues
Classifier: Programming Language :: Python :: 3
Classifier: License :: OSI Approved :: MIT License
Classifier: Operating System :: OS Independent
Requires-Python: >=3.8
License-File: LICENSE
Requires-Dist: scanpy >=1.9.3
Requires-Dist: numpy
Requires-Dist: pandas
Requires-Dist: anndata
Requires-Dist: matplotlib
Requires-Dist: scipy
Requires-Dist: scikit-learn
Requires-Dist: psutil
Requires-Dist: tqdm
Requires-Dist: leidenalg
Requires-Dist: torch >=2.0
Requires-Dist: torchvision
